SpeechDelay/__init__.py
SpeechDelay/speechdelay.py
speechdelay-1.0.1.dist-info/METADATA
speechdelay-1.0.1.dist-info/WHEEL
speechdelay-1.0.1.dist-info/licenses/LICENSE.txt
speechdelay-1.0.1.dist-info/RECORD
