Metadata-Version: 2.1
Name: speechdelay
Version: 1.0.1
Summary: A simple package that can delay the output of letters in text and color the text in the process.
Author-email: AuraPy <zayanarshad@aurapy.co.uk>
License-File: LICENSE.txt
Classifier: License :: OSI Approved :: GNU General Public License v3 (GPLv3)
Classifier: Operating System :: Microsoft :: Windows
Classifier: Programming Language :: Python :: 3
Requires-Python: >=3.9
Requires-Dist: colorama
